ofrapi/__init__.py
ofrapi/bsrm/__init__.py
ofrapi/fsi/__init__.py
ofrapi/hfm/__init__.py
ofrapi/hfm/get_series_data.py
ofrapi/hfm/get_series_info.py
ofrapi/hfm/series_info_data.py
ofrapi/stfm/__init__.py
ofrapi/stfm/get_series_data.py
ofrapi/stfm/get_series_info.py
ofrapi/stfm/series_info_data.py
ofrapi/tests/__init__.py
ofrapi/tests/test_bsrm.py
ofrapi/tests/test_fsi.py
ofrapi/tests/test_hfm.py
ofrapi/tests/test_stfm.py
ofrapi-0.0.5.dist-info/LICENSE
ofrapi-0.0.5.dist-info/METADATA
ofrapi-0.0.5.dist-info/WHEEL
ofrapi-0.0.5.dist-info/top_level.txt
ofrapi-0.0.5.dist-info/RECORD
