Metadata-Version: 2.1
Name: ofrapi
Version: 0.0.5
Summary: Python API wrapper for Office of Financial Research (OFR)
Home-page: https://github.com/Jaldekoa/ofrapi
Author: Jon Aldekoa
Author-email: jaldekoa@gmail.com
License: MIT License
Platform: Any
Classifier: Development Status :: 3 - Alpha
Classifier: Intended Audience :: Education
Classifier: Intended Audience :: Financial and Insurance Industry
Classifier: Intended Audience :: Science/Research
Classifier: Programming Language :: Python
Classifier: Programming Language :: Python :: 3
Classifier: Operating System :: OS Independent
Classifier: Programming Language :: Python :: 3.9
Classifier: Programming Language :: Python :: 3.10
Classifier: Programming Language :: Python :: 3.11
Classifier: Programming Language :: Python :: 3.12
Classifier: License :: OSI Approved :: MIT License
License-File: LICENSE
Requires-Dist: setuptools >=68.2
Requires-Dist: pandas >=2.0.0
Requires-Dist: requests >=2.23.0
Requires-Dist: openpyxl >=3.1.0
